palombe/__init__.py
palombe-0.3.2.dist-info/LICENSE
palombe-0.3.2.dist-info/METADATA
palombe-0.3.2.dist-info/WHEEL
palombe-0.3.2.dist-info/top_level.txt
palombe-0.3.2.dist-info/RECORD
