Metadata-Version: 2.1
Name: palombe
Version: 0.3.2
Summary: Palombe lets you send and receive messages synchronously through different processes using named pipes
Home-page: http://github.com/yvan-sraka/palombe-python
Author: Yvan Sraka
Author-email: yvan@sraka.pw
License: UNKNOWN
Platform: UNKNOWN
Classifier: Programming Language :: Python :: 3
Classifier: License :: OSI Approved :: GNU General Public License v3 (GPLv3)
Classifier: Operating System :: Unix
